pydebuginfod/__init__.py
pydebuginfod/pydebuginfod.py
pydebuginfod-0.2.0.dist-info/WHEEL
pydebuginfod-0.2.0.dist-info/METADATA
pydebuginfod-0.2.0.dist-info/RECORD
