Metadata-Version: 2.1
Name: pydebuginfod
Version: 0.2.0
Summary: A python client for the debuginfod server
License: MIT
Author: Matt Schulte
Author-email: schultetwin1@gmail.com
Requires-Python: >=3.6,<4.0
Classifier: License :: OSI Approved :: MIT License
Classifier: Programming Language :: Python :: 3
Classifier: Programming Language :: Python :: 3.6
Classifier: Programming Language :: Python :: 3.7
Classifier: Programming Language :: Python :: 3.8
Classifier: Programming Language :: Python :: 3.9
Requires-Dist: bison (>=0.1.2,<0.2.0)
Requires-Dist: boto3 (>=1.17.22,<2.0.0)
Requires-Dist: requests (>=2.25.1,<3.0.0)
Requires-Dist: toml (>=0.10.2,<0.11.0)
Requires-Dist: xdgappdirs (>=1.4.5,<2.0.0)
